coqpit/__init__.py
coqpit/coqpit.py
coqpit-0.0.16.dist-info/LICENSE.txt
coqpit-0.0.16.dist-info/METADATA
coqpit-0.0.16.dist-info/WHEEL
coqpit-0.0.16.dist-info/top_level.txt
coqpit-0.0.16.dist-info/RECORD
