Metadata-Version: 2.1
Name: coqpit
Version: 0.0.16
Summary: Simple (maybe too simple), light-weight config management through python data-classes.
Home-page: https://github.com/erogol/coqpit
Author: Eren Gölge
Author-email: egolge@coqui.ai
License: UNKNOWN
Project-URL: Tracker, https://github.com/coqui-ai/coqpit/issues
Project-URL: Repository, https://github.com/coqui-ai/coqpit
Project-URL: Discussions, https://github.com/coqui-ai/coqpit/discussions
Platform: UNKNOWN
Classifier: Programming Language :: Python
Classifier: Programming Language :: Python :: 3
Classifier: Development Status :: 4 - Beta
Classifier: Intended Audience :: Developers
Classifier: Operating System :: POSIX :: Linux
Classifier: Operating System :: MacOS
Classifier: Operating System :: Microsoft :: Windows
Requires-Python: >=3.6.0
License-File: LICENSE.txt
Requires-Dist: dataclasses ; python_version == "3.6"
